Automation/Automation.py
Automation/__init__.py
Automation/cli.py
Patient_Ward_Automation-0.1.0.dist-info/AUTHORS.rst
Patient_Ward_Automation-0.1.0.dist-info/LICENSE
Patient_Ward_Automation-0.1.0.dist-info/METADATA
Patient_Ward_Automation-0.1.0.dist-info/WHEEL
Patient_Ward_Automation-0.1.0.dist-info/entry_points.txt
Patient_Ward_Automation-0.1.0.dist-info/top_level.txt
Patient_Ward_Automation-0.1.0.dist-info/zip-safe
Patient_Ward_Automation-0.1.0.dist-info/RECORD
