Metadata-Version: 2.1
Name: Patient-Ward-Automation
Version: 0.1.0
Summary: Python Boilerplate contains all the boilerplate you need to create a Python package.
Home-page: https://github.com/CassandraDacha/Automation
Author: Cassandra Dacha
Author-email: cassie.dacha@gmail.com
License: MIT license
Download-URL: https://github.com/CassandraDacha/Automation/archive/v_01.tar.gz
Keywords: Automation
Platform: UNKNOWN
Classifier: Development Status :: 2 - Pre-Alpha
Classifier: Intended Audience :: Developers
Classifier: License :: OSI Approved :: MIT License
Classifier: Natural Language :: English
Classifier: Programming Language :: Python :: 3
Classifier: Programming Language :: Python :: 3.5
Classifier: Programming Language :: Python :: 3.6
Classifier: Programming Language :: Python :: 3.7
Classifier: Programming Language :: Python :: 3.8
Requires-Python: >=3.5
Requires-Dist: Click (>=7.0)
